{
  "@class" : "org.sehkah.ddon.tools.extractor.common.logic.resource.entity.ui.MsgSet",
  "FileHeader" : {
    "MagicBytesLength" : 4,
    "MagicString" : "mgst",
    "VersionBytesLength" : 2,
    "VersionNumber" : 3
  },
  "FileSize" : 1348,
  "NativeMsgDataArrayNum" : 25,
  "NativeMsgGroupArray" : [ {
    "@class" : "org.sehkah.ddon.tools.extractor.common.logic.resource.entity.ui.MsgGroup",
    "GroupNameSerial" : 0,
    "GroupSerial" : 17633,
    "GroupType" : 0,
    "GroupTypeName" : "MSG_GROUP_TYPE_NONE",
    "MsgData" : [ {
      "@class" : "org.sehkah.ddon.tools.extractor.common.logic.resource.entity.ui.MsgData",
      "DispTime" : 0,
      "DispType" : 0,
      "GmdIndex" : 0,
      "JumpGroupSerial" : 0,
      "Message" : {
        "En" : "",
        "Jp" : "ふむ、白竜様からの力は受け取っておる\nお前さんにこの技を伝えるかどうか\nわしが品定めしろということじゃな"
      },
      "MsgSerial" : 446107,
      "MsgType" : 0,
      "SetMotion" : 0,
      "TalkFaceType" : 0,
      "VoiceReqNo" : -1
    }, {
      "@class" : "org.sehkah.ddon.tools.extractor.common.logic.resource.entity.ui.MsgData",
      "DispTime" : 0,
      "DispType" : 0,
      "GmdIndex" : 1,
      "JumpGroupSerial" : 0,
      "Message" : {
        "En" : "",
        "Jp" : "どれほど護り、鍛えてきたか――\n実戦で見せてもらうことにしようかの\n試練の場で落ち合おうぞ"
      },
      "MsgSerial" : 483844,
      "MsgType" : 0,
      "SetMotion" : 0,
      "TalkFaceType" : 0,
      "VoiceReqNo" : -1
    } ],
    "NameDispOff" : false,
    "NpcId" : 4500,
    "NpcName" : {
      "En" : "Rudolfo",
      "Jp" : "ルドルフォ"
    }
  }, {
    "@class" : "org.sehkah.ddon.tools.extractor.common.logic.resource.entity.ui.MsgGroup",
    "GroupNameSerial" : 0,
    "GroupSerial" : 17634,
    "GroupType" : 0,
    "GroupTypeName" : "MSG_GROUP_TYPE_NONE",
    "MsgData" : [ {
      "@class" : "org.sehkah.ddon.tools.extractor.common.logic.resource.entity.ui.MsgData",
      "DispTime" : 0,
      "DispType" : 0,
      "GmdIndex" : 2,
      "JumpGroupSerial" : 0,
      "Message" : {
        "En" : "",
        "Jp" : "どれほど護り、鍛えてきたか――\n実戦で見せてもらうことにしようかの\n試練の場で落ち合おうぞ"
      },
      "MsgSerial" : 446108,
      "MsgType" : 0,
      "SetMotion" : 0,
      "TalkFaceType" : 0,
      "VoiceReqNo" : -1
    } ],
    "NameDispOff" : false,
    "NpcId" : 4500,
    "NpcName" : {
      "En" : "Rudolfo",
      "Jp" : "ルドルフォ"
    }
  }, {
    "@class" : "org.sehkah.ddon.tools.extractor.common.logic.resource.entity.ui.MsgGroup",
    "GroupNameSerial" : 0,
    "GroupSerial" : 17635,
    "GroupType" : 0,
    "GroupTypeName" : "MSG_GROUP_TYPE_NONE",
    "MsgData" : [ {
      "@class" : "org.sehkah.ddon.tools.extractor.common.logic.resource.entity.ui.MsgData",
      "DispTime" : 0,
      "DispType" : 0,
      "GmdIndex" : 3,
      "JumpGroupSerial" : 0,
      "Message" : {
        "En" : "",
        "Jp" : "来たか\n今回はワシも共に戦場を駆けるとしよう\nより近くで見定めさせてもらうぞ"
      },
      "MsgSerial" : 446109,
      "MsgType" : 0,
      "SetMotion" : 0,
      "TalkFaceType" : 0,
      "VoiceReqNo" : -1
    } ],
    "NameDispOff" : false,
    "NpcId" : 4500,
    "NpcName" : {
      "En" : "Rudolfo",
      "Jp" : "ルドルフォ"
    }
  }, {
    "@class" : "org.sehkah.ddon.tools.extractor.common.logic.resource.entity.ui.MsgGroup",
    "GroupNameSerial" : 0,
    "GroupSerial" : 17982,
    "GroupType" : 0,
    "GroupTypeName" : "MSG_GROUP_TYPE_NONE",
    "MsgData" : [ {
      "@class" : "org.sehkah.ddon.tools.extractor.common.logic.resource.entity.ui.MsgData",
      "DispTime" : 0,
      "DispType" : 0,
      "GmdIndex" : 4,
      "JumpGroupSerial" : 0,
      "Message" : {
        "En" : "",
        "Jp" : "お前さんの積み重ねてきた\"砦\"\n見せてもらおうかの"
      },
      "MsgSerial" : 451694,
      "MsgType" : 0,
      "SetMotion" : 0,
      "TalkFaceType" : 0,
      "VoiceReqNo" : -1
    } ],
    "NameDispOff" : false,
    "NpcId" : 4500,
    "NpcName" : {
      "En" : "Rudolfo",
      "Jp" : "ルドルフォ"
    }
  }, {
    "@class" : "org.sehkah.ddon.tools.extractor.common.logic.resource.entity.ui.MsgGroup",
    "GroupNameSerial" : 0,
    "GroupSerial" : 18409,
    "GroupType" : 0,
    "GroupTypeName" : "MSG_GROUP_TYPE_NONE",
    "MsgData" : [ {
      "@class" : "org.sehkah.ddon.tools.extractor.common.logic.resource.entity.ui.MsgData",
      "DispTime" : 0,
      "DispType" : 0,
      "GmdIndex" : 5,
      "JumpGroupSerial" : 0,
      "Message" : {
        "En" : "",
        "Jp" : "ほれ、最初の試練が出たぞ"
      },
      "MsgSerial" : 481770,
      "MsgType" : 0,
      "SetMotion" : 0,
      "TalkFaceType" : 0,
      "VoiceReqNo" : -1
    } ],
    "NameDispOff" : false,
    "NpcId" : 4500,
    "NpcName" : {
      "En" : "Rudolfo",
      "Jp" : "ルドルフォ"
    }
  }, {
    "@class" : "org.sehkah.ddon.tools.extractor.common.logic.resource.entity.ui.MsgGroup",
    "GroupNameSerial" : 0,
    "GroupSerial" : 18410,
    "GroupType" : 0,
    "GroupTypeName" : "MSG_GROUP_TYPE_NONE",
    "MsgData" : [ {
      "@class" : "org.sehkah.ddon.tools.extractor.common.logic.resource.entity.ui.MsgData",
      "DispTime" : 0,
      "DispType" : 0,
      "GmdIndex" : 6,
      "JumpGroupSerial" : 0,
      "Message" : {
        "En" : "",
        "Jp" : "その調子じゃ\n次は第二の試練の場所へ向かうぞ"
      },
      "MsgSerial" : 481771,
      "MsgType" : 0,
      "SetMotion" : 0,
      "TalkFaceType" : 0,
      "VoiceReqNo" : -1
    } ],
    "NameDispOff" : false,
    "NpcId" : 4500,
    "NpcName" : {
      "En" : "Rudolfo",
      "Jp" : "ルドルフォ"
    }
  }, {
    "@class" : "org.sehkah.ddon.tools.extractor.common.logic.resource.entity.ui.MsgGroup",
    "GroupNameSerial" : 0,
    "GroupSerial" : 18411,
    "GroupType" : 0,
    "GroupTypeName" : "MSG_GROUP_TYPE_NONE",
    "MsgData" : [ {
      "@class" : "org.sehkah.ddon.tools.extractor.common.logic.resource.entity.ui.MsgData",
      "DispTime" : 0,
      "DispType" : 0,
      "GmdIndex" : 7,
      "JumpGroupSerial" : 0,
      "Message" : {
        "En" : "",
        "Jp" : "見つけたか、これが第二の試練じゃ"
      },
      "MsgSerial" : 481772,
      "MsgType" : 0,
      "SetMotion" : 0,
      "TalkFaceType" : 0,
      "VoiceReqNo" : -1
    } ],
    "NameDispOff" : false,
    "NpcId" : 4500,
    "NpcName" : {
      "En" : "Rudolfo",
      "Jp" : "ルドルフォ"
    }
  }, {
    "@class" : "org.sehkah.ddon.tools.extractor.common.logic.resource.entity.ui.MsgGroup",
    "GroupNameSerial" : 0,
    "GroupSerial" : 18412,
    "GroupType" : 0,
    "GroupTypeName" : "MSG_GROUP_TYPE_NONE",
    "MsgData" : [ {
      "@class" : "org.sehkah.ddon.tools.extractor.common.logic.resource.entity.ui.MsgData",
      "DispTime" : 0,
      "DispType" : 0,
      "GmdIndex" : 8,
      "JumpGroupSerial" : 0,
      "Message" : {
        "En" : "",
        "Jp" : "よしよし、次が最後の試練じゃ"
      },
      "MsgSerial" : 481773,
      "MsgType" : 0,
      "SetMotion" : 0,
      "TalkFaceType" : 0,
      "VoiceReqNo" : -1
    } ],
    "NameDispOff" : false,
    "NpcId" : 4500,
    "NpcName" : {
      "En" : "Rudolfo",
      "Jp" : "ルドルフォ"
    }
  }, {
    "@class" : "org.sehkah.ddon.tools.extractor.common.logic.resource.entity.ui.MsgGroup",
    "GroupNameSerial" : 0,
    "GroupSerial" : 17983,
    "GroupType" : 0,
    "GroupTypeName" : "MSG_GROUP_TYPE_NONE",
    "MsgData" : [ {
      "@class" : "org.sehkah.ddon.tools.extractor.common.logic.resource.entity.ui.MsgData",
      "DispTime" : 0,
      "DispType" : 0,
      "GmdIndex" : 9,
      "JumpGroupSerial" : 0,
      "Message" : {
        "En" : "",
        "Jp" : "これが最後の試練じゃぞ！"
      },
      "MsgSerial" : 451695,
      "MsgType" : 0,
      "SetMotion" : 0,
      "TalkFaceType" : 0,
      "VoiceReqNo" : -1
    } ],
    "NameDispOff" : false,
    "NpcId" : 4500,
    "NpcName" : {
      "En" : "Rudolfo",
      "Jp" : "ルドルフォ"
    }
  }, {
    "@class" : "org.sehkah.ddon.tools.extractor.common.logic.resource.entity.ui.MsgGroup",
    "GroupNameSerial" : 0,
    "GroupSerial" : 17984,
    "GroupType" : 0,
    "GroupTypeName" : "MSG_GROUP_TYPE_NONE",
    "MsgData" : [ {
      "@class" : "org.sehkah.ddon.tools.extractor.common.logic.resource.entity.ui.MsgData",
      "DispTime" : 0,
      "DispType" : 0,
      "GmdIndex" : 10,
      "JumpGroupSerial" : 0,
      "Message" : {
        "En" : "",
        "Jp" : "お前さんの戦いぶり、その精神力\nしかと見届けた！\n新たな技の継承の儀式は灯台に戻って行おうかの"
      },
      "MsgSerial" : 451696,
      "MsgType" : 0,
      "SetMotion" : 0,
      "TalkFaceType" : 0,
      "VoiceReqNo" : -1
    } ],
    "NameDispOff" : false,
    "NpcId" : 4500,
    "NpcName" : {
      "En" : "Rudolfo",
      "Jp" : "ルドルフォ"
    }
  }, {
    "@class" : "org.sehkah.ddon.tools.extractor.common.logic.resource.entity.ui.MsgGroup",
    "GroupNameSerial" : 0,
    "GroupSerial" : 17636,
    "GroupType" : 0,
    "GroupTypeName" : "MSG_GROUP_TYPE_NONE",
    "MsgData" : [ {
      "@class" : "org.sehkah.ddon.tools.extractor.common.logic.resource.entity.ui.MsgData",
      "DispTime" : 0,
      "DispType" : 0,
      "GmdIndex" : 11,
      "JumpGroupSerial" : 0,
      "Message" : {
        "En" : "",
        "Jp" : "お前さんの戦いぶり、その精神力\nしかと見届けた！"
      },
      "MsgSerial" : 446110,
      "MsgType" : 0,
      "SetMotion" : 0,
      "TalkFaceType" : 0,
      "VoiceReqNo" : -1
    }, {
      "@class" : "org.sehkah.ddon.tools.extractor.common.logic.resource.entity.ui.MsgData",
      "DispTime" : 0,
      "DispType" : 0,
      "GmdIndex" : 12,
      "JumpGroupSerial" : 0,
      "Message" : {
        "En" : "",
        "Jp" : "新たな技の継承の儀式は灯台に戻って行おうかの\n――さて、帰るとするか"
      },
      "MsgSerial" : 485933,
      "MsgType" : 0,
      "SetMotion" : 0,
      "TalkFaceType" : 0,
      "VoiceReqNo" : -1
    } ],
    "NameDispOff" : false,
    "NpcId" : 4500,
    "NpcName" : {
      "En" : "Rudolfo",
      "Jp" : "ルドルフォ"
    }
  }, {
    "@class" : "org.sehkah.ddon.tools.extractor.common.logic.resource.entity.ui.MsgGroup",
    "GroupNameSerial" : 0,
    "GroupSerial" : 17637,
    "GroupType" : 0,
    "GroupTypeName" : "MSG_GROUP_TYPE_NONE",
    "MsgData" : [ {
      "@class" : "org.sehkah.ddon.tools.extractor.common.logic.resource.entity.ui.MsgData",
      "DispTime" : 0,
      "DispType" : 0,
      "GmdIndex" : 13,
      "JumpGroupSerial" : 0,
      "Message" : {
        "En" : "",
        "Jp" : "己自身を仲間を守る砦とし\n戦いの行方を導く確かな灯台となる\n――そんなシールドセージに\nお前さんは確かに近づいておるようじゃ"
      },
      "MsgSerial" : 446111,
      "MsgType" : 0,
      "SetMotion" : 0,
      "TalkFaceType" : 0,
      "VoiceReqNo" : -1
    }, {
      "@class" : "org.sehkah.ddon.tools.extractor.common.logic.resource.entity.ui.MsgData",
      "DispTime" : 0,
      "DispType" : 0,
      "GmdIndex" : 14,
      "JumpGroupSerial" : 0,
      "Message" : {
        "En" : "",
        "Jp" : "白竜様から賜りしこの技を使うにふさわしい\nこれからもさらに精進するようにな"
      },
      "MsgSerial" : 483845,
      "MsgType" : 0,
      "SetMotion" : 0,
      "TalkFaceType" : 0,
      "VoiceReqNo" : -1
    } ],
    "NameDispOff" : false,
    "NpcId" : 4500,
    "NpcName" : {
      "En" : "Rudolfo",
      "Jp" : "ルドルフォ"
    }
  }, {
    "@class" : "org.sehkah.ddon.tools.extractor.common.logic.resource.entity.ui.MsgGroup",
    "GroupNameSerial" : 0,
    "GroupSerial" : 18229,
    "GroupType" : 0,
    "GroupTypeName" : "MSG_GROUP_TYPE_NONE",
    "MsgData" : [ {
      "@class" : "org.sehkah.ddon.tools.extractor.common.logic.resource.entity.ui.MsgData",
      "DispTime" : 0,
      "DispType" : 0,
      "GmdIndex" : 15,
      "JumpGroupSerial" : 0,
      "Message" : {
        "En" : "",
        "Jp" : "シールドセージはみなの砦であり灯台でもあるぞ"
      },
      "MsgSerial" : 477210,
      "MsgType" : 0,
      "SetMotion" : 0,
      "TalkFaceType" : 0,
      "VoiceReqNo" : -1
    } ],
    "NameDispOff" : false,
    "NpcId" : 4500,
    "NpcName" : {
      "En" : "Rudolfo",
      "Jp" : "ルドルフォ"
    }
  }, {
    "@class" : "org.sehkah.ddon.tools.extractor.common.logic.resource.entity.ui.MsgGroup",
    "GroupNameSerial" : 0,
    "GroupSerial" : 18230,
    "GroupType" : 0,
    "GroupTypeName" : "MSG_GROUP_TYPE_NONE",
    "MsgData" : [ {
      "@class" : "org.sehkah.ddon.tools.extractor.common.logic.resource.entity.ui.MsgData",
      "DispTime" : 0,
      "DispType" : 0,
      "GmdIndex" : 16,
      "JumpGroupSerial" : 0,
      "Message" : {
        "En" : "",
        "Jp" : "敵の攻撃を受け止め、反撃の力とするのじゃ"
      },
      "MsgSerial" : 477211,
      "MsgType" : 0,
      "SetMotion" : 0,
      "TalkFaceType" : 0,
      "VoiceReqNo" : -1
    } ],
    "NameDispOff" : false,
    "NpcId" : 4500,
    "NpcName" : {
      "En" : "Rudolfo",
      "Jp" : "ルドルフォ"
    }
  }, {
    "@class" : "org.sehkah.ddon.tools.extractor.common.logic.resource.entity.ui.MsgGroup",
    "GroupNameSerial" : 0,
    "GroupSerial" : 18231,
    "GroupType" : 0,
    "GroupTypeName" : "MSG_GROUP_TYPE_NONE",
    "MsgData" : [ {
      "@class" : "org.sehkah.ddon.tools.extractor.common.logic.resource.entity.ui.MsgData",
      "DispTime" : 0,
      "DispType" : 0,
      "GmdIndex" : 17,
      "JumpGroupSerial" : 0,
      "Message" : {
        "En" : "",
        "Jp" : "敵の弱点属性を見極めることが大事じゃぞ"
      },
      "MsgSerial" : 477212,
      "MsgType" : 0,
      "SetMotion" : 0,
      "TalkFaceType" : 0,
      "VoiceReqNo" : -1
    } ],
    "NameDispOff" : false,
    "NpcId" : 4500,
    "NpcName" : {
      "En" : "Rudolfo",
      "Jp" : "ルドルフォ"
    }
  }, {
    "@class" : "org.sehkah.ddon.tools.extractor.common.logic.resource.entity.ui.MsgGroup",
    "GroupNameSerial" : 0,
    "GroupSerial" : 18232,
    "GroupType" : 0,
    "GroupTypeName" : "MSG_GROUP_TYPE_NONE",
    "MsgData" : [ {
      "@class" : "org.sehkah.ddon.tools.extractor.common.logic.resource.entity.ui.MsgData",
      "DispTime" : 0,
      "DispType" : 0,
      "GmdIndex" : 18,
      "JumpGroupSerial" : 0,
      "Message" : {
        "En" : "",
        "Jp" : "味方がいるなら、その能力も把握しておくんじゃ"
      },
      "MsgSerial" : 477213,
      "MsgType" : 0,
      "SetMotion" : 0,
      "TalkFaceType" : 0,
      "VoiceReqNo" : -1
    } ],
    "NameDispOff" : false,
    "NpcId" : 4500,
    "NpcName" : {
      "En" : "Rudolfo",
      "Jp" : "ルドルフォ"
    }
  }, {
    "@class" : "org.sehkah.ddon.tools.extractor.common.logic.resource.entity.ui.MsgGroup",
    "GroupNameSerial" : 0,
    "GroupSerial" : 18233,
    "GroupType" : 0,
    "GroupTypeName" : "MSG_GROUP_TYPE_NONE",
    "MsgData" : [ {
      "@class" : "org.sehkah.ddon.tools.extractor.common.logic.resource.entity.ui.MsgData",
      "DispTime" : 0,
      "DispType" : 0,
      "GmdIndex" : 19,
      "JumpGroupSerial" : 0,
      "Message" : {
        "En" : "",
        "Jp" : "属性を見極めた者が戦いを制するのじゃ"
      },
      "MsgSerial" : 477214,
      "MsgType" : 0,
      "SetMotion" : 0,
      "TalkFaceType" : 0,
      "VoiceReqNo" : -1
    } ],
    "NameDispOff" : false,
    "NpcId" : 4500,
    "NpcName" : {
      "En" : "Rudolfo",
      "Jp" : "ルドルフォ"
    }
  }, {
    "@class" : "org.sehkah.ddon.tools.extractor.common.logic.resource.entity.ui.MsgGroup",
    "GroupNameSerial" : 0,
    "GroupSerial" : 18236,
    "GroupType" : 0,
    "GroupTypeName" : "MSG_GROUP_TYPE_NONE",
    "MsgData" : [ {
      "@class" : "org.sehkah.ddon.tools.extractor.common.logic.resource.entity.ui.MsgData",
      "DispTime" : 0,
      "DispType" : 0,
      "GmdIndex" : 20,
      "JumpGroupSerial" : 0,
      "Message" : {
        "En" : "",
        "Jp" : "敵の弱点属性は把握しておるか？"
      },
      "MsgSerial" : 477217,
      "MsgType" : 0,
      "SetMotion" : 0,
      "TalkFaceType" : 0,
      "VoiceReqNo" : -1
    } ],
    "NameDispOff" : false,
    "NpcId" : 4500,
    "NpcName" : {
      "En" : "Rudolfo",
      "Jp" : "ルドルフォ"
    }
  }, {
    "@class" : "org.sehkah.ddon.tools.extractor.common.logic.resource.entity.ui.MsgGroup",
    "GroupNameSerial" : 0,
    "GroupSerial" : 18237,
    "GroupType" : 0,
    "GroupTypeName" : "MSG_GROUP_TYPE_NONE",
    "MsgData" : [ {
      "@class" : "org.sehkah.ddon.tools.extractor.common.logic.resource.entity.ui.MsgData",
      "DispTime" : 0,
      "DispType" : 0,
      "GmdIndex" : 21,
      "JumpGroupSerial" : 0,
      "Message" : {
        "En" : "",
        "Jp" : "攻守の切替は自分にあった間合いをとるのじゃ"
      },
      "MsgSerial" : 477218,
      "MsgType" : 0,
      "SetMotion" : 0,
      "TalkFaceType" : 0,
      "VoiceReqNo" : -1
    } ],
    "NameDispOff" : false,
    "NpcId" : 4500,
    "NpcName" : {
      "En" : "Rudolfo",
      "Jp" : "ルドルフォ"
    }
  }, {
    "@class" : "org.sehkah.ddon.tools.extractor.common.logic.resource.entity.ui.MsgGroup",
    "GroupNameSerial" : 0,
    "GroupSerial" : 18238,
    "GroupType" : 0,
    "GroupTypeName" : "MSG_GROUP_TYPE_NONE",
    "MsgData" : [ {
      "@class" : "org.sehkah.ddon.tools.extractor.common.logic.resource.entity.ui.MsgData",
      "DispTime" : 0,
      "DispType" : 0,
      "GmdIndex" : 22,
      "JumpGroupSerial" : 0,
      "Message" : {
        "En" : "",
        "Jp" : "状態異常を与えるタイミングも大事じゃな"
      },
      "MsgSerial" : 477219,
      "MsgType" : 0,
      "SetMotion" : 0,
      "TalkFaceType" : 0,
      "VoiceReqNo" : -1
    } ],
    "NameDispOff" : false,
    "NpcId" : 4500,
    "NpcName" : {
      "En" : "Rudolfo",
      "Jp" : "ルドルフォ"
    }
  }, {
    "@class" : "org.sehkah.ddon.tools.extractor.common.logic.resource.entity.ui.MsgGroup",
    "GroupNameSerial" : 0,
    "GroupSerial" : 18234,
    "GroupType" : 0,
    "GroupTypeName" : "MSG_GROUP_TYPE_NONE",
    "MsgData" : [ {
      "@class" : "org.sehkah.ddon.tools.extractor.common.logic.resource.entity.ui.MsgData",
      "DispTime" : 0,
      "DispType" : 0,
      "GmdIndex" : 23,
      "JumpGroupSerial" : 0,
      "Message" : {
        "En" : "",
        "Jp" : "攻撃を防御してフォースバーストが基本じゃ"
      },
      "MsgSerial" : 477215,
      "MsgType" : 0,
      "SetMotion" : 0,
      "TalkFaceType" : 0,
      "VoiceReqNo" : -1
    } ],
    "NameDispOff" : false,
    "NpcId" : 4500,
    "NpcName" : {
      "En" : "Rudolfo",
      "Jp" : "ルドルフォ"
    }
  }, {
    "@class" : "org.sehkah.ddon.tools.extractor.common.logic.resource.entity.ui.MsgGroup",
    "GroupNameSerial" : 0,
    "GroupSerial" : 18235,
    "GroupType" : 0,
    "GroupTypeName" : "MSG_GROUP_TYPE_NONE",
    "MsgData" : [ {
      "@class" : "org.sehkah.ddon.tools.extractor.common.logic.resource.entity.ui.MsgData",
      "DispTime" : 0,
      "DispType" : 0,
      "GmdIndex" : 24,
      "JumpGroupSerial" : 0,
      "Message" : {
        "En" : "",
        "Jp" : "敵の動きを見極めることが肝心じゃ"
      },
      "MsgSerial" : 477216,
      "MsgType" : 0,
      "SetMotion" : 0,
      "TalkFaceType" : 0,
      "VoiceReqNo" : -1
    } ],
    "NameDispOff" : false,
    "NpcId" : 4500,
    "NpcName" : {
      "En" : "Rudolfo",
      "Jp" : "ルドルフォ"
    }
  } ],
  "NativeMsgGroupArrayNum" : 22
}