{
  "@class" : "org.sehkah.ddon.tools.extractor.common.logic.resource.entity.ui.MsgSet",
  "FileHeader" : {
    "MagicBytesLength" : 4,
    "MagicString" : "mgst",
    "VersionBytesLength" : 2,
    "VersionNumber" : 3
  },
  "FileSize" : 1570,
  "NativeMsgDataArrayNum" : 38,
  "NativeMsgGroupArray" : [ {
    "@class" : "org.sehkah.ddon.tools.extractor.common.logic.resource.entity.ui.MsgGroup",
    "GroupNameSerial" : 0,
    "GroupSerial" : 18499,
    "GroupType" : 0,
    "GroupTypeName" : "MSG_GROUP_TYPE_NONE",
    "MsgData" : [ {
      "@class" : "org.sehkah.ddon.tools.extractor.common.logic.resource.entity.ui.MsgData",
      "DispTime" : 0,
      "DispType" : 0,
      "GmdIndex" : 0,
      "JumpGroupSerial" : 0,
      "Message" : {
        "En" : "",
        "Jp" : "ねぇねぇ――知ってる？\n\"怪盗団\"が現れたんだって！\nあたしたちの間じゃ、その噂でもちきりなの"
      },
      "MsgSerial" : 494914,
      "MsgType" : 0,
      "SetMotion" : 0,
      "TalkFaceType" : 0,
      "VoiceReqNo" : -1
    }, {
      "@class" : "org.sehkah.ddon.tools.extractor.common.logic.resource.entity.ui.MsgData",
      "DispTime" : 0,
      "DispType" : 0,
      "GmdIndex" : 1,
      "JumpGroupSerial" : 0,
      "Message" : {
        "En" : "",
        "Jp" : "実はね、あたし――怪盗に会った事あるんだ\nそれどころか、助けてもらったの\n気が付いたら、このカードを握っていた――\nよく覚えてないけど、きっとそれが証拠よね？"
      },
      "MsgSerial" : 503293,
      "MsgType" : 0,
      "SetMotion" : 0,
      "TalkFaceType" : 0,
      "VoiceReqNo" : -1
    }, {
      "@class" : "org.sehkah.ddon.tools.extractor.common.logic.resource.entity.ui.MsgData",
      "DispTime" : 0,
      "DispType" : 0,
      "GmdIndex" : 2,
      "JumpGroupSerial" : 0,
      "Message" : {
        "En" : "",
        "Jp" : "なに、これが欲しいって――\nちょっと、本気で言ってるの？\n――そうね、じゃああたしのお願い聞いてくれたら\n考えてあげてもいいわよ"
      },
      "MsgSerial" : 503294,
      "MsgType" : 0,
      "SetMotion" : 0,
      "TalkFaceType" : 0,
      "VoiceReqNo" : -1
    }, {
      "@class" : "org.sehkah.ddon.tools.extractor.common.logic.resource.entity.ui.MsgData",
      "DispTime" : 0,
      "DispType" : 0,
      "GmdIndex" : 3,
      "JumpGroupSerial" : 0,
      "Message" : {
        "En" : "",
        "Jp" : "彼氏と度胸試しに《血すすぎ河原》へ行く予定なの\nだけど、万一何かあると嫌だから――\nあなた腕が立ちそうだし、掃除してきてほしいの\n魔物一匹残らずよ！　よろしくね"
      },
      "MsgSerial" : 503295,
      "MsgType" : 0,
      "SetMotion" : 0,
      "TalkFaceType" : 0,
      "VoiceReqNo" : -1
    } ],
    "NameDispOff" : false,
    "NpcId" : 4725,
    "NpcName" : {
      "En" : "Marisa",
      "Jp" : "マリサ"
    }
  }, {
    "@class" : "org.sehkah.ddon.tools.extractor.common.logic.resource.entity.ui.MsgGroup",
    "GroupNameSerial" : 0,
    "GroupSerial" : 18500,
    "GroupType" : 0,
    "GroupTypeName" : "MSG_GROUP_TYPE_NONE",
    "MsgData" : [ {
      "@class" : "org.sehkah.ddon.tools.extractor.common.logic.resource.entity.ui.MsgData",
      "DispTime" : 0,
      "DispType" : 0,
      "GmdIndex" : 4,
      "JumpGroupSerial" : 0,
      "Message" : {
        "En" : "",
        "Jp" : "そんなもの欲しそうな目で見られたって\nこのカードはあげないわよ――タダでは、ね"
      },
      "MsgSerial" : 494915,
      "MsgType" : 0,
      "SetMotion" : 0,
      "TalkFaceType" : 0,
      "VoiceReqNo" : -1
    }, {
      "@class" : "org.sehkah.ddon.tools.extractor.common.logic.resource.entity.ui.MsgData",
      "DispTime" : 0,
      "DispType" : 0,
      "GmdIndex" : 5,
      "JumpGroupSerial" : 0,
      "Message" : {
        "En" : "",
        "Jp" : "さぁ、さっさと《血すすぎ河原》へ行って\nあたしと彼のために、危険な魔物を\n掃除してきてちょうだいな"
      },
      "MsgSerial" : 503296,
      "MsgType" : 0,
      "SetMotion" : 0,
      "TalkFaceType" : 0,
      "VoiceReqNo" : -1
    } ],
    "NameDispOff" : false,
    "NpcId" : 4725,
    "NpcName" : {
      "En" : "Marisa",
      "Jp" : "マリサ"
    }
  }, {
    "@class" : "org.sehkah.ddon.tools.extractor.common.logic.resource.entity.ui.MsgGroup",
    "GroupNameSerial" : 0,
    "GroupSerial" : 18501,
    "GroupType" : 0,
    "GroupTypeName" : "MSG_GROUP_TYPE_NONE",
    "MsgData" : [ {
      "@class" : "org.sehkah.ddon.tools.extractor.common.logic.resource.entity.ui.MsgData",
      "DispTime" : 0,
      "DispType" : 0,
      "GmdIndex" : 6,
      "JumpGroupSerial" : 0,
      "Message" : {
        "En" : "",
        "Jp" : "やだ――本当に行ってきたの？\nしかも、ちゃんと魔物も片づけてきてくれたんだ――\n諦めると思ったのに、結構根性あるのね"
      },
      "MsgSerial" : 494916,
      "MsgType" : 0,
      "SetMotion" : 0,
      "TalkFaceType" : 0,
      "VoiceReqNo" : -1
    }, {
      "@class" : "org.sehkah.ddon.tools.extractor.common.logic.resource.entity.ui.MsgData",
      "DispTime" : 0,
      "DispType" : 0,
      "GmdIndex" : 7,
      "JumpGroupSerial" : 0,
      "Message" : {
        "En" : "",
        "Jp" : "ホント――あなたの事、見直しちゃった\nねぇ――こんなカードより\nもっとイイものあげよっか――？"
      },
      "MsgSerial" : 503297,
      "MsgType" : 0,
      "SetMotion" : 0,
      "TalkFaceType" : 0,
      "VoiceReqNo" : -1
    }, {
      "@class" : "org.sehkah.ddon.tools.extractor.common.logic.resource.entity.ui.MsgData",
      "DispTime" : 0,
      "DispType" : 0,
      "GmdIndex" : 8,
      "JumpGroupSerial" : 0,
      "Message" : {
        "En" : "",
        "Jp" : "うそうそ――冗談よ、冗談\nそんなに怖い顔しないでよ\n危ない目に遭わせちゃったんだし、\nお礼はちゃんとするってば"
      },
      "MsgSerial" : 503298,
      "MsgType" : 0,
      "SetMotion" : 0,
      "TalkFaceType" : 0,
      "VoiceReqNo" : -1
    }, {
      "@class" : "org.sehkah.ddon.tools.extractor.common.logic.resource.entity.ui.MsgData",
      "DispTime" : 0,
      "DispType" : 0,
      "GmdIndex" : 9,
      "JumpGroupSerial" : 0,
      "Message" : {
        "En" : "",
        "Jp" : "こんな小さな村だから、あたしの噂はすぐに広まって\n今まで話した事もない輩まで押しかけて来るの――\nそんな奴らを煙に巻く癖が、つい出ちゃったみたい\n――とにかく、デート楽しんでくるわ！　ありがとね"
      },
      "MsgSerial" : 503299,
      "MsgType" : 0,
      "SetMotion" : 0,
      "TalkFaceType" : 0,
      "VoiceReqNo" : -1
    } ],
    "NameDispOff" : false,
    "NpcId" : 4725,
    "NpcName" : {
      "En" : "Marisa",
      "Jp" : "マリサ"
    }
  }, {
    "@class" : "org.sehkah.ddon.tools.extractor.common.logic.resource.entity.ui.MsgGroup",
    "GroupNameSerial" : 0,
    "GroupSerial" : 18579,
    "GroupType" : 0,
    "GroupTypeName" : "MSG_GROUP_TYPE_NONE",
    "MsgData" : [ {
      "@class" : "org.sehkah.ddon.tools.extractor.common.logic.resource.entity.ui.MsgData",
      "DispTime" : 0,
      "DispType" : 0,
      "GmdIndex" : 10,
      "JumpGroupSerial" : 0,
      "Message" : {
        "En" : "",
        "Jp" : "怪盗が姿を現したって噂の場所は、\n《廃屋の地下室》よ――"
      },
      "MsgSerial" : 494920,
      "MsgType" : 0,
      "SetMotion" : 0,
      "TalkFaceType" : 0,
      "VoiceReqNo" : -1
    }, {
      "@class" : "org.sehkah.ddon.tools.extractor.common.logic.resource.entity.ui.MsgData",
      "DispTime" : 0,
      "DispType" : 0,
      "GmdIndex" : 11,
      "JumpGroupSerial" : 0,
      "Message" : {
        "En" : "",
        "Jp" : "え？　彼氏はどうしたって？\n相手は怪盗よ！\nつまんない彼氏なんかと比べないでよ"
      },
      "MsgSerial" : 505875,
      "MsgType" : 0,
      "SetMotion" : 0,
      "TalkFaceType" : 0,
      "VoiceReqNo" : -1
    } ],
    "NameDispOff" : false,
    "NpcId" : 4725,
    "NpcName" : {
      "En" : "Marisa",
      "Jp" : "マリサ"
    }
  }, {
    "@class" : "org.sehkah.ddon.tools.extractor.common.logic.resource.entity.ui.MsgGroup",
    "GroupNameSerial" : 0,
    "GroupSerial" : 18582,
    "GroupType" : 0,
    "GroupTypeName" : "MSG_GROUP_TYPE_NONE",
    "MsgData" : [ {
      "@class" : "org.sehkah.ddon.tools.extractor.common.logic.resource.entity.ui.MsgData",
      "DispTime" : 0,
      "DispType" : 0,
      "GmdIndex" : 12,
      "JumpGroupSerial" : 0,
      "Message" : {
        "En" : "",
        "Jp" : "ああ、覚者さん！　\n本当に行ってきてくれたのね――\nどうだった？"
      },
      "MsgSerial" : 494923,
      "MsgType" : 0,
      "SetMotion" : 0,
      "TalkFaceType" : 0,
      "VoiceReqNo" : -1
    }, {
      "@class" : "org.sehkah.ddon.tools.extractor.common.logic.resource.entity.ui.MsgData",
      "DispTime" : 0,
      "DispType" : 0,
      "GmdIndex" : 13,
      "JumpGroupSerial" : 0,
      "Message" : {
        "En" : "",
        "Jp" : "いたのは魔物だけで、怪盗の痕跡は特に無し――\nそう、残念だわ\nだけど、行ってきてくれてありがとう"
      },
      "MsgSerial" : 505876,
      "MsgType" : 0,
      "SetMotion" : 0,
      "TalkFaceType" : 0,
      "VoiceReqNo" : -1
    }, {
      "@class" : "org.sehkah.ddon.tools.extractor.common.logic.resource.entity.ui.MsgData",
      "DispTime" : 0,
      "DispType" : 0,
      "GmdIndex" : 14,
      "JumpGroupSerial" : 0,
      "Message" : {
        "En" : "",
        "Jp" : "――正直言うと、怪盗の記憶はほとんど無いの\n何を言っていたかわからなかったし、\n顔もぼんやりとしか――\nだけど、あの頼もしい腕の感触だけは覚えてるわ"
      },
      "MsgSerial" : 505877,
      "MsgType" : 0,
      "SetMotion" : 0,
      "TalkFaceType" : 0,
      "VoiceReqNo" : -1
    }, {
      "@class" : "org.sehkah.ddon.tools.extractor.common.logic.resource.entity.ui.MsgData",
      "DispTime" : 0,
      "DispType" : 0,
      "GmdIndex" : 15,
      "JumpGroupSerial" : 0,
      "Message" : {
        "En" : "",
        "Jp" : "ちょっと謎めいた感じだったけど――\n彼氏――ルキーノとは逆のタイプだったから、\n久しぶりにときめいちゃったの\nああ、ルキーノにも、そんな所があればいいのに――"
      },
      "MsgSerial" : 505878,
      "MsgType" : 0,
      "SetMotion" : 0,
      "TalkFaceType" : 0,
      "VoiceReqNo" : -1
    } ],
    "NameDispOff" : false,
    "NpcId" : 4725,
    "NpcName" : {
      "En" : "Marisa",
      "Jp" : "マリサ"
    }
  }, {
    "@class" : "org.sehkah.ddon.tools.extractor.common.logic.resource.entity.ui.MsgGroup",
    "GroupNameSerial" : 0,
    "GroupSerial" : 18502,
    "GroupType" : 0,
    "GroupTypeName" : "MSG_GROUP_TYPE_NONE",
    "MsgData" : [ {
      "@class" : "org.sehkah.ddon.tools.extractor.common.logic.resource.entity.ui.MsgData",
      "DispTime" : 0,
      "DispType" : 0,
      "GmdIndex" : 16,
      "JumpGroupSerial" : 0,
      "Message" : {
        "En" : "",
        "Jp" : "ねぇねぇ――知ってる？\n今話題の\"怪盗団\"の噂！\n実はね、あたし――怪盗に会った事あるんだ"
      },
      "MsgSerial" : 494917,
      "MsgType" : 0,
      "SetMotion" : 0,
      "TalkFaceType" : 0,
      "VoiceReqNo" : -1
    }, {
      "@class" : "org.sehkah.ddon.tools.extractor.common.logic.resource.entity.ui.MsgData",
      "DispTime" : 0,
      "DispType" : 0,
      "GmdIndex" : 17,
      "JumpGroupSerial" : 0,
      "Message" : {
        "En" : "",
        "Jp" : "それどころか、助けてもらったの\nあの日から、あの人の事が忘れられなくて――\n顔は分からなかったけど、ワイルドで素敵な人だった\nこのレスタニアでは見ないタイプね"
      },
      "MsgSerial" : 505879,
      "MsgType" : 0,
      "SetMotion" : 0,
      "TalkFaceType" : 0,
      "VoiceReqNo" : -1
    }, {
      "@class" : "org.sehkah.ddon.tools.extractor.common.logic.resource.entity.ui.MsgData",
      "DispTime" : 0,
      "DispType" : 0,
      "GmdIndex" : 18,
      "JumpGroupSerial" : 0,
      "Message" : {
        "En" : "",
        "Jp" : "ねぇ、あなたこのカードが欲しいんでしょう？\nこの怪盗のマークが書かれたカード――\nだったら、見てきてほしい場所があるの\n最近怪盗が姿を見せたって噂の場所――"
      },
      "MsgSerial" : 505880,
      "MsgType" : 0,
      "SetMotion" : 0,
      "TalkFaceType" : 0,
      "VoiceReqNo" : -1
    }, {
      "@class" : "org.sehkah.ddon.tools.extractor.common.logic.resource.entity.ui.MsgData",
      "DispTime" : 0,
      "DispType" : 0,
      "GmdIndex" : 19,
      "JumpGroupSerial" : 0,
      "Message" : {
        "En" : "",
        "Jp" : "《廃屋の地下室》ってところ\n危険があるかもしれないから――\n怪盗が本当にそこにいたのか、\n見て来てもらえる？"
      },
      "MsgSerial" : 505881,
      "MsgType" : 0,
      "SetMotion" : 0,
      "TalkFaceType" : 0,
      "VoiceReqNo" : -1
    } ],
    "NameDispOff" : false,
    "NpcId" : 4725,
    "NpcName" : {
      "En" : "Marisa",
      "Jp" : "マリサ"
    }
  }, {
    "@class" : "org.sehkah.ddon.tools.extractor.common.logic.resource.entity.ui.MsgGroup",
    "GroupNameSerial" : 0,
    "GroupSerial" : 18580,
    "GroupType" : 0,
    "GroupTypeName" : "MSG_GROUP_TYPE_NONE",
    "MsgData" : [ {
      "@class" : "org.sehkah.ddon.tools.extractor.common.logic.resource.entity.ui.MsgData",
      "DispTime" : 0,
      "DispType" : 0,
      "GmdIndex" : 20,
      "JumpGroupSerial" : 0,
      "Message" : {
        "En" : "",
        "Jp" : "《狩人の抜け穴》へ行って、様子を見て来てほしいの\nそこが、あたしが怪盗に助けてもらった場所――\nえ？　怪盗に出会えたらどうするかって？\nそうね――怪盗団に入れてもらおうかな"
      },
      "MsgSerial" : 494921,
      "MsgType" : 0,
      "SetMotion" : 0,
      "TalkFaceType" : 0,
      "VoiceReqNo" : -1
    } ],
    "NameDispOff" : false,
    "NpcId" : 4725,
    "NpcName" : {
      "En" : "Marisa",
      "Jp" : "マリサ"
    }
  }, {
    "@class" : "org.sehkah.ddon.tools.extractor.common.logic.resource.entity.ui.MsgGroup",
    "GroupNameSerial" : 0,
    "GroupSerial" : 18583,
    "GroupType" : 0,
    "GroupTypeName" : "MSG_GROUP_TYPE_NONE",
    "MsgData" : [ {
      "@class" : "org.sehkah.ddon.tools.extractor.common.logic.resource.entity.ui.MsgData",
      "DispTime" : 0,
      "DispType" : 0,
      "GmdIndex" : 21,
      "JumpGroupSerial" : 0,
      "Message" : {
        "En" : "",
        "Jp" : "ああ、覚者さん！　\n本当に行ってきてくれたのね――\nどんな場所だった？"
      },
      "MsgSerial" : 494924,
      "MsgType" : 0,
      "SetMotion" : 0,
      "TalkFaceType" : 0,
      "VoiceReqNo" : -1
    }, {
      "@class" : "org.sehkah.ddon.tools.extractor.common.logic.resource.entity.ui.MsgData",
      "DispTime" : 0,
      "DispType" : 0,
      "GmdIndex" : 22,
      "JumpGroupSerial" : 0,
      "Message" : {
        "En" : "",
        "Jp" : "――普通の洞窟？\nそんな馬鹿な――いいえ、よくは覚えてないんだけど\nもっと、特徴的な場所だったような――\nレスタニアで、見た事も聞いた事もない所だったの"
      },
      "MsgSerial" : 505882,
      "MsgType" : 0,
      "SetMotion" : 0,
      "TalkFaceType" : 0,
      "VoiceReqNo" : -1
    }, {
      "@class" : "org.sehkah.ddon.tools.extractor.common.logic.resource.entity.ui.MsgData",
      "DispTime" : 0,
      "DispType" : 0,
      "GmdIndex" : 23,
      "JumpGroupSerial" : 0,
      "Message" : {
        "En" : "",
        "Jp" : "一体どうなっているの――\n夢でも見ていたのかしら？\nこのカードも、もしかしたら\n誰かのイタズラだったのかも――"
      },
      "MsgSerial" : 505883,
      "MsgType" : 0,
      "SetMotion" : 0,
      "TalkFaceType" : 0,
      "VoiceReqNo" : -1
    }, {
      "@class" : "org.sehkah.ddon.tools.extractor.common.logic.resource.entity.ui.MsgData",
      "DispTime" : 0,
      "DispType" : 0,
      "GmdIndex" : 24,
      "JumpGroupSerial" : 0,
      "Message" : {
        "En" : "",
        "Jp" : "――とにかく、行ってきてくれてありがとね\nお礼はちゃんとするつもりよ\nほら、これが欲しいのよね？\nもう何のカードか定かじゃないけど――もらってよ"
      },
      "MsgSerial" : 505884,
      "MsgType" : 0,
      "SetMotion" : 0,
      "TalkFaceType" : 0,
      "VoiceReqNo" : -1
    } ],
    "NameDispOff" : false,
    "NpcId" : 4725,
    "NpcName" : {
      "En" : "Marisa",
      "Jp" : "マリサ"
    }
  }, {
    "@class" : "org.sehkah.ddon.tools.extractor.common.logic.resource.entity.ui.MsgGroup",
    "GroupNameSerial" : 0,
    "GroupSerial" : 18503,
    "GroupType" : 0,
    "GroupTypeName" : "MSG_GROUP_TYPE_NONE",
    "MsgData" : [ {
      "@class" : "org.sehkah.ddon.tools.extractor.common.logic.resource.entity.ui.MsgData",
      "DispTime" : 0,
      "DispType" : 0,
      "GmdIndex" : 25,
      "JumpGroupSerial" : 0,
      "Message" : {
        "En" : "",
        "Jp" : "ねぇねぇ――知ってる？\n\"怪盗団\"が現れたんだって！\n今じゃ、その噂でもちきりよ"
      },
      "MsgSerial" : 494918,
      "MsgType" : 0,
      "SetMotion" : 0,
      "TalkFaceType" : 0,
      "VoiceReqNo" : -1
    }, {
      "@class" : "org.sehkah.ddon.tools.extractor.common.logic.resource.entity.ui.MsgData",
      "DispTime" : 0,
      "DispType" : 0,
      "GmdIndex" : 26,
      "JumpGroupSerial" : 0,
      "Message" : {
        "En" : "",
        "Jp" : "実はね、あたし――怪盗に会った事あるんだ\nそれどころか、助けてもらったの\nよく覚えてないんだけど――\nどこかに迷い込んで、そこから助けてもらったような"
      },
      "MsgSerial" : 505885,
      "MsgType" : 0,
      "SetMotion" : 0,
      "TalkFaceType" : 0,
      "VoiceReqNo" : -1
    }, {
      "@class" : "org.sehkah.ddon.tools.extractor.common.logic.resource.entity.ui.MsgData",
      "DispTime" : 0,
      "DispType" : 0,
      "GmdIndex" : 27,
      "JumpGroupSerial" : 0,
      "Message" : {
        "En" : "",
        "Jp" : "それで、いつの間にかこのカードを握っていたの\n――言わなくても分かるわ、これが欲しいんでしょ？\n最近そういう人ばかりなの、あたしの周り\nそうね――じゃあ、あたしのお願い聞いてくれる？"
      },
      "MsgSerial" : 505886,
      "MsgType" : 0,
      "SetMotion" : 0,
      "TalkFaceType" : 0,
      "VoiceReqNo" : -1
    }, {
      "@class" : "org.sehkah.ddon.tools.extractor.common.logic.resource.entity.ui.MsgData",
      "DispTime" : 0,
      "DispType" : 0,
      "GmdIndex" : 28,
      "JumpGroupSerial" : 0,
      "Message" : {
        "En" : "",
        "Jp" : "《狩人の抜け穴》へ行って、様子を見て来てほしいの\nあたしが怪盗と会った場所――\n覚えている特徴を挙げると、そこが怪しいみたいなの\nもし怪盗を見かけたら、すぐに教えてね"
      },
      "MsgSerial" : 505887,
      "MsgType" : 0,
      "SetMotion" : 0,
      "TalkFaceType" : 0,
      "VoiceReqNo" : -1
    } ],
    "NameDispOff" : false,
    "NpcId" : 4725,
    "NpcName" : {
      "En" : "Marisa",
      "Jp" : "マリサ"
    }
  }, {
    "@class" : "org.sehkah.ddon.tools.extractor.common.logic.resource.entity.ui.MsgGroup",
    "GroupNameSerial" : 0,
    "GroupSerial" : 18581,
    "GroupType" : 0,
    "GroupTypeName" : "MSG_GROUP_TYPE_NONE",
    "MsgData" : [ {
      "@class" : "org.sehkah.ddon.tools.extractor.common.logic.resource.entity.ui.MsgData",
      "DispTime" : 0,
      "DispType" : 0,
      "GmdIndex" : 29,
      "JumpGroupSerial" : 0,
      "Message" : {
        "En" : "",
        "Jp" : "《死者の小窟》で怪盗捜索中の騎士団が\n集まっていたから、あなたに見て来てほしいの\n――もし何も無かったら、縁が無かったんだと思って\nすっぱり諦めるわ"
      },
      "MsgSerial" : 494922,
      "MsgType" : 0,
      "SetMotion" : 0,
      "TalkFaceType" : 0,
      "VoiceReqNo" : -1
    } ],
    "NameDispOff" : false,
    "NpcId" : 4726,
    "NpcName" : {
      "En" : "Julia",
      "Jp" : "ジュリア"
    }
  }, {
    "@class" : "org.sehkah.ddon.tools.extractor.common.logic.resource.entity.ui.MsgGroup",
    "GroupNameSerial" : 0,
    "GroupSerial" : 18584,
    "GroupType" : 0,
    "GroupTypeName" : "MSG_GROUP_TYPE_NONE",
    "MsgData" : [ {
      "@class" : "org.sehkah.ddon.tools.extractor.common.logic.resource.entity.ui.MsgData",
      "DispTime" : 0,
      "DispType" : 0,
      "GmdIndex" : 30,
      "JumpGroupSerial" : 0,
      "Message" : {
        "En" : "",
        "Jp" : "ああ、覚者さん！　\n本当に行ってきてくれたのね――\nそこには何があったの？"
      },
      "MsgSerial" : 494925,
      "MsgType" : 0,
      "SetMotion" : 0,
      "TalkFaceType" : 0,
      "VoiceReqNo" : -1
    }, {
      "@class" : "org.sehkah.ddon.tools.extractor.common.logic.resource.entity.ui.MsgData",
      "DispTime" : 0,
      "DispType" : 0,
      "GmdIndex" : 31,
      "JumpGroupSerial" : 0,
      "Message" : {
        "En" : "",
        "Jp" : "――魔物だけ、か\n騎士団が集まっていたのは、魔物のせいだったのね\nこれで完全に万策尽きたわ――"
      },
      "MsgSerial" : 505888,
      "MsgType" : 0,
      "SetMotion" : 0,
      "TalkFaceType" : 0,
      "VoiceReqNo" : -1
    }, {
      "@class" : "org.sehkah.ddon.tools.extractor.common.logic.resource.entity.ui.MsgData",
      "DispTime" : 0,
      "DispType" : 0,
      "GmdIndex" : 32,
      "JumpGroupSerial" : 0,
      "Message" : {
        "En" : "",
        "Jp" : "ええ、分かってる\nもう怪盗を追いかけるのはこれっきり！\nあーあ、つまんない――\n平凡な毎日が、何か変わると思ってたのに"
      },
      "MsgSerial" : 505889,
      "MsgType" : 0,
      "SetMotion" : 0,
      "TalkFaceType" : 0,
      "VoiceReqNo" : -1
    }, {
      "@class" : "org.sehkah.ddon.tools.extractor.common.logic.resource.entity.ui.MsgData",
      "DispTime" : 0,
      "DispType" : 0,
      "GmdIndex" : 33,
      "JumpGroupSerial" : 0,
      "Message" : {
        "En" : "",
        "Jp" : "ほら、このカードが欲しかったんでしょ？\nお礼にあげるわ――もうあたしには必要ないから\n明日からは――心に仮面をつけてでも\n退屈に向き合っていかなきゃね"
      },
      "MsgSerial" : 505890,
      "MsgType" : 0,
      "SetMotion" : 0,
      "TalkFaceType" : 0,
      "VoiceReqNo" : -1
    } ],
    "NameDispOff" : false,
    "NpcId" : 4725,
    "NpcName" : {
      "En" : "Marisa",
      "Jp" : "マリサ"
    }
  }, {
    "@class" : "org.sehkah.ddon.tools.extractor.common.logic.resource.entity.ui.MsgGroup",
    "GroupNameSerial" : 0,
    "GroupSerial" : 18504,
    "GroupType" : 0,
    "GroupTypeName" : "MSG_GROUP_TYPE_NONE",
    "MsgData" : [ {
      "@class" : "org.sehkah.ddon.tools.extractor.common.logic.resource.entity.ui.MsgData",
      "DispTime" : 0,
      "DispType" : 0,
      "GmdIndex" : 34,
      "JumpGroupSerial" : 0,
      "Message" : {
        "En" : "",
        "Jp" : "ねぇねぇ――知ってる？\n\"怪盗団\"が現れた、って噂！\n実は、あたし怪盗に助けてもらったことが\nあるんだけど――"
      },
      "MsgSerial" : 494919,
      "MsgType" : 0,
      "SetMotion" : 0,
      "TalkFaceType" : 0,
      "VoiceReqNo" : -1
    }, {
      "@class" : "org.sehkah.ddon.tools.extractor.common.logic.resource.entity.ui.MsgData",
      "DispTime" : 0,
      "DispType" : 0,
      "GmdIndex" : 35,
      "JumpGroupSerial" : 0,
      "Message" : {
        "En" : "",
        "Jp" : "これだけ一生懸命探してるのに、尻尾も掴めないのよ\n――ま、当然か\n騎士団が必死になって探してるものを\nあたしがそう簡単に見つけられるはずないわよね――"
      },
      "MsgSerial" : 505891,
      "MsgType" : 0,
      "SetMotion" : 0,
      "TalkFaceType" : 0,
      "VoiceReqNo" : -1
    }, {
      "@class" : "org.sehkah.ddon.tools.extractor.common.logic.resource.entity.ui.MsgData",
      "DispTime" : 0,
      "DispType" : 0,
      "GmdIndex" : 36,
      "JumpGroupSerial" : 0,
      "Message" : {
        "En" : "",
        "Jp" : "だけど、助けてもらったときに\nいつの間にか握っていたこのカード――\nきっとこれは何かの意味があると思うのよね\n――ねぇ、あなたにお願いがあるの"
      },
      "MsgSerial" : 505892,
      "MsgType" : 0,
      "SetMotion" : 0,
      "TalkFaceType" : 0,
      "VoiceReqNo" : -1
    }, {
      "@class" : "org.sehkah.ddon.tools.extractor.common.logic.resource.entity.ui.MsgData",
      "DispTime" : 0,
      "DispType" : 0,
      "GmdIndex" : 37,
      "JumpGroupSerial" : 0,
      "Message" : {
        "En" : "",
        "Jp" : "怪盗捜索中の騎士団が《死者の小窟》に\n集まっていたのをさっき見たわ\nあそこにはきっと何かある――\n危険かもしれないけど、様子を見て来てほしいの！"
      },
      "MsgSerial" : 505893,
      "MsgType" : 0,
      "SetMotion" : 0,
      "TalkFaceType" : 0,
      "VoiceReqNo" : -1
    } ],
    "NameDispOff" : false,
    "NpcId" : 4725,
    "NpcName" : {
      "En" : "Marisa",
      "Jp" : "マリサ"
    }
  } ],
  "NativeMsgGroupArrayNum" : 12
}