{
  "@class" : "org.sehkah.ddon.tools.extractor.common.logic.resource.entity.ui.MsgSet",
  "FileHeader" : {
    "MagicBytesLength" : 4,
    "MagicString" : "mgst",
    "VersionBytesLength" : 2,
    "VersionNumber" : 3
  },
  "FileSize" : 1892,
  "NativeMsgDataArrayNum" : 41,
  "NativeMsgGroupArray" : [ {
    "@class" : "org.sehkah.ddon.tools.extractor.common.logic.resource.entity.ui.MsgGroup",
    "GroupNameSerial" : 0,
    "GroupSerial" : 15601,
    "GroupType" : 0,
    "GroupTypeName" : "MSG_GROUP_TYPE_NONE",
    "MsgData" : [ {
      "@class" : "org.sehkah.ddon.tools.extractor.common.logic.resource.entity.ui.MsgData",
      "DispTime" : 0,
      "DispType" : 0,
      "GmdIndex" : 0,
      "JumpGroupSerial" : 0,
      "Message" : {
        "En" : "The messenger has just informed me\nthat the gate to the island has opened.",
        "Jp" : "今しがた島のゲートが開通したと\n使者が伝えてきた"
      },
      "MsgSerial" : 377533,
      "MsgType" : 0,
      "SetMotion" : 0,
      "TalkFaceType" : 0,
      "VoiceReqNo" : -1
    }, {
      "@class" : "org.sehkah.ddon.tools.extractor.common.logic.resource.entity.ui.MsgData",
      "DispTime" : 0,
      "DispType" : 0,
      "GmdIndex" : 1,
      "JumpGroupSerial" : 0,
      "Message" : {
        "En" : "It appears that Cecily's depletion, \nwhich was concerning,\nis not as bad as we had feared.\nYet, there is no assurance that the gate\nwill remain stable.",
        "Jp" : "懸念されたセシリーの消耗は\nさほどではないとのことだ\nだが、ゲートが安定し続ける保証はない"
      },
      "MsgSerial" : 377535,
      "MsgType" : 0,
      "SetMotion" : 0,
      "TalkFaceType" : 0,
      "VoiceReqNo" : -1
    }, {
      "@class" : "org.sehkah.ddon.tools.extractor.common.logic.resource.entity.ui.MsgData",
      "DispTime" : 0,
      "DispType" : 0,
      "GmdIndex" : 2,
      "JumpGroupSerial" : 0,
      "Message" : {
        "En" : "It seems Cecily is eager to cross to Phindym\nright away, but if something were to happen there,\nthe effects on us would be incalculable.",
        "Jp" : "セシリーはすぐにでもフィンダムへ\n渡りたいと主張しているらしいが\n向こうで万が一のことが起これば\n我々への影響は計り知れない"
      },
      "MsgSerial" : 377536,
      "MsgType" : 0,
      "SetMotion" : 0,
      "TalkFaceType" : 0,
      "VoiceReqNo" : -1
    }, {
      "@class" : "org.sehkah.ddon.tools.extractor.common.logic.resource.entity.ui.MsgData",
      "DispTime" : 0,
      "DispType" : 0,
      "GmdIndex" : 3,
      "JumpGroupSerial" : 0,
      "Message" : {
        "En" : "Thus―― \nYou will cross to Phindym with Cecily\nand the others as their escort.\nIt is necessary to have someone to understand\nthe situation and carry out a field survey.\nUndoubtedly, there is no one more qualified\nfor this task than you.",
        "Jp" : "そこで――\nセシリーたちとフィンダムへ渡り、護衛し\n状況の把握――実地の調査を行う者が必要だ\nもちろん、おまえ以上の適任はいない"
      },
      "MsgSerial" : 377537,
      "MsgType" : 0,
      "SetMotion" : 0,
      "TalkFaceType" : 0,
      "VoiceReqNo" : -1
    }, {
      "@class" : "org.sehkah.ddon.tools.extractor.common.logic.resource.entity.ui.MsgData",
      "DispTime" : 0,
      "DispType" : 0,
      "GmdIndex" : 4,
      "JumpGroupSerial" : 0,
      "Message" : {
        "En" : "The first investigation team—your subordinates—\nare already waiting at the gate.",
        "Jp" : "すでに第一次調査隊――おまえの部下たちは\nゲートの前で待っている"
      },
      "MsgSerial" : 377538,
      "MsgType" : 0,
      "SetMotion" : 0,
      "TalkFaceType" : 0,
      "VoiceReqNo" : -1
    }, {
      "@class" : "org.sehkah.ddon.tools.extractor.common.logic.resource.entity.ui.MsgData",
      "DispTime" : 0,
      "DispType" : 0,
      "GmdIndex" : 5,
      "JumpGroupSerial" : 0,
      "Message" : {
        "En" : "With the perspective of one who grew up\nin Lestania, having faced many dangers,\nplease assess the situation.",
        "Jp" : "幾多の危機を乗り越えたレスタニア育ちの目で\n状況を見極めてくれ"
      },
      "MsgSerial" : 377539,
      "MsgType" : 0,
      "SetMotion" : 0,
      "TalkFaceType" : 0,
      "VoiceReqNo" : -1
    } ],
    "NameDispOff" : false,
    "NpcId" : 4,
    "NpcName" : {
      "En" : "Joseph",
      "Jp" : "ジョゼフ"
    }
  }, {
    "@class" : "org.sehkah.ddon.tools.extractor.common.logic.resource.entity.ui.MsgGroup",
    "GroupNameSerial" : 0,
    "GroupSerial" : 17180,
    "GroupType" : 0,
    "GroupTypeName" : "MSG_GROUP_TYPE_NONE",
    "MsgData" : [ {
      "@class" : "org.sehkah.ddon.tools.extractor.common.logic.resource.entity.ui.MsgData",
      "DispTime" : 0,
      "DispType" : 0,
      "GmdIndex" : 6,
      "JumpGroupSerial" : 0,
      "Message" : {
        "En" : "Be sure to observe what kind of place it is\nover there and what is occurring.",
        "Jp" : "向こうがどんなところで、何が起こっているのか\nよく見てくるのだぞ"
      },
      "MsgSerial" : 434475,
      "MsgType" : 0,
      "SetMotion" : 0,
      "TalkFaceType" : 0,
      "VoiceReqNo" : -1
    } ],
    "NameDispOff" : false,
    "NpcId" : 4,
    "NpcName" : {
      "En" : "Joseph",
      "Jp" : "ジョゼフ"
    }
  }, {
    "@class" : "org.sehkah.ddon.tools.extractor.common.logic.resource.entity.ui.MsgGroup",
    "GroupNameSerial" : 0,
    "GroupSerial" : 17181,
    "GroupType" : 0,
    "GroupTypeName" : "MSG_GROUP_TYPE_NONE",
    "MsgData" : [ {
      "@class" : "org.sehkah.ddon.tools.extractor.common.logic.resource.entity.ui.MsgData",
      "DispTime" : 0,
      "DispType" : 0,
      "GmdIndex" : 7,
      "JumpGroupSerial" : 0,
      "Message" : {
        "En" : "What may be familiar to Cecily and Loeg\ncould pose some danger for you. \nI believe there is at least a small risk involved.",
        "Jp" : "セシリーやロイグにとっては馴れたことでも\n君たちにとっては危険だってことが\n少なからずあると思う"
      },
      "MsgSerial" : 434476,
      "MsgType" : 0,
      "SetMotion" : 0,
      "TalkFaceType" : 0,
      "VoiceReqNo" : -1
    }, {
      "@class" : "org.sehkah.ddon.tools.extractor.common.logic.resource.entity.ui.MsgData",
      "DispTime" : 0,
      "DispType" : 0,
      "GmdIndex" : 8,
      "JumpGroupSerial" : 0,
      "Message" : {
        "En" : "Keep your eyes peeled and listen\nattentively to your surroundings―― okay?",
        "Jp" : "目を凝らして、耳を澄まして――いいね？"
      },
      "MsgSerial" : 434477,
      "MsgType" : 0,
      "SetMotion" : 0,
      "TalkFaceType" : 0,
      "VoiceReqNo" : -1
    } ],
    "NameDispOff" : false,
    "NpcId" : 3,
    "NpcName" : {
      "En" : "Klaus",
      "Jp" : "クラウス"
    }
  }, {
    "@class" : "org.sehkah.ddon.tools.extractor.common.logic.resource.entity.ui.MsgGroup",
    "GroupNameSerial" : 0,
    "GroupSerial" : 15602,
    "GroupType" : 0,
    "GroupTypeName" : "MSG_GROUP_TYPE_NONE",
    "MsgData" : [ {
      "@class" : "org.sehkah.ddon.tools.extractor.common.logic.resource.entity.ui.MsgData",
      "DispTime" : 0,
      "DispType" : 0,
      "GmdIndex" : 9,
      "JumpGroupSerial" : 0,
      "Message" : {
        "En" : "When I was invited to a friend's home \nfor the first time―― \nWhen I tasted the unknown fruit――",
        "Jp" : "友の家に初めて招かれた時――\n未知の果実を口にする時――"
      },
      "MsgSerial" : 377534,
      "MsgType" : 0,
      "SetMotion" : 0,
      "TalkFaceType" : 0,
      "VoiceReqNo" : -1
    }, {
      "@class" : "org.sehkah.ddon.tools.extractor.common.logic.resource.entity.ui.MsgData",
      "DispTime" : 0,
      "DispType" : 0,
      "GmdIndex" : 10,
      "JumpGroupSerial" : 0,
      "Message" : {
        "En" : "When I hear the reading of the words\nof the renowned poet――\nAll of this, it's a risk we take.",
        "Jp" : "評判の詩人の朗読を聞く時――\nこりゃ、全部、冒険だ"
      },
      "MsgSerial" : 377540,
      "MsgType" : 0,
      "SetMotion" : 0,
      "TalkFaceType" : 0,
      "VoiceReqNo" : -1
    }, {
      "@class" : "org.sehkah.ddon.tools.extractor.common.logic.resource.entity.ui.MsgData",
      "DispTime" : 0,
      "DispType" : 0,
      "GmdIndex" : 11,
      "JumpGroupSerial" : 0,
      "Message" : {
        "En" : "Naturally, to step into the unknown world \nis the greatest of adventures.",
        "Jp" : "もちろん、まだ見ぬ世界に乗り込むのは\nとびきりの大冒険"
      },
      "MsgSerial" : 377541,
      "MsgType" : 0,
      "SetMotion" : 0,
      "TalkFaceType" : 0,
      "VoiceReqNo" : -1
    }, {
      "@class" : "org.sehkah.ddon.tools.extractor.common.logic.resource.entity.ui.MsgData",
      "DispTime" : 0,
      "DispType" : 0,
      "GmdIndex" : 12,
      "JumpGroupSerial" : 0,
      "Message" : {
        "En" : "There will be challenges, but do not fear. \nEnjoy it to its fullest extent!",
        "Jp" : "困難もあるだろうが、怖れるな\n目一杯楽しんでやれ"
      },
      "MsgSerial" : 377542,
      "MsgType" : 0,
      "SetMotion" : 0,
      "TalkFaceType" : 0,
      "VoiceReqNo" : -1
    }, {
      "@class" : "org.sehkah.ddon.tools.extractor.common.logic.resource.entity.ui.MsgData",
      "DispTime" : 0,
      "DispType" : 0,
      "GmdIndex" : 13,
      "JumpGroupSerial" : 0,
      "Message" : {
        "En" : "Not everyone can embark on an adventure.",
        "Jp" : "冒険なんて、誰もができることじゃないからな"
      },
      "MsgSerial" : 377543,
      "MsgType" : 0,
      "SetMotion" : 0,
      "TalkFaceType" : 0,
      "VoiceReqNo" : -1
    } ],
    "NameDispOff" : false,
    "NpcId" : 1035,
    "NpcName" : {
      "En" : "Zerkin",
      "Jp" : "ゼルキン"
    }
  }, {
    "@class" : "org.sehkah.ddon.tools.extractor.common.logic.resource.entity.ui.MsgGroup",
    "GroupNameSerial" : 0,
    "GroupSerial" : 17182,
    "GroupType" : 0,
    "GroupTypeName" : "MSG_GROUP_TYPE_NONE",
    "MsgData" : [ {
      "@class" : "org.sehkah.ddon.tools.extractor.common.logic.resource.entity.ui.MsgData",
      "DispTime" : 0,
      "DispType" : 0,
      "GmdIndex" : 14,
      "JumpGroupSerial" : 0,
      "Message" : {
        "En" : "Look, the gate is stable.",
        "Jp" : "見てください\nゲートは安定しています"
      },
      "MsgSerial" : 434478,
      "MsgType" : 0,
      "SetMotion" : 0,
      "TalkFaceType" : 0,
      "VoiceReqNo" : -1
    } ],
    "NameDispOff" : false,
    "NpcId" : 20,
    "NpcName" : {
      "En" : "Cecily",
      "Jp" : "セシリー"
    }
  }, {
    "@class" : "org.sehkah.ddon.tools.extractor.common.logic.resource.entity.ui.MsgGroup",
    "GroupNameSerial" : 0,
    "GroupSerial" : 17183,
    "GroupType" : 0,
    "GroupTypeName" : "MSG_GROUP_TYPE_NONE",
    "MsgData" : [ {
      "@class" : "org.sehkah.ddon.tools.extractor.common.logic.resource.entity.ui.MsgData",
      "DispTime" : 0,
      "DispType" : 0,
      "GmdIndex" : 15,
      "JumpGroupSerial" : 0,
      "Message" : {
        "En" : "It's finally time.",
        "Jp" : "いよいよだね"
      },
      "MsgSerial" : 434479,
      "MsgType" : 0,
      "SetMotion" : 0,
      "TalkFaceType" : 0,
      "VoiceReqNo" : -1
    } ],
    "NameDispOff" : false,
    "NpcId" : 22,
    "NpcName" : {
      "En" : "Loeg",
      "Jp" : "ロイグ"
    }
  }, {
    "@class" : "org.sehkah.ddon.tools.extractor.common.logic.resource.entity.ui.MsgGroup",
    "GroupNameSerial" : 0,
    "GroupSerial" : 17184,
    "GroupType" : 0,
    "GroupTypeName" : "MSG_GROUP_TYPE_NONE",
    "MsgData" : [ {
      "@class" : "org.sehkah.ddon.tools.extractor.common.logic.resource.entity.ui.MsgData",
      "DispTime" : 0,
      "DispType" : 0,
      "GmdIndex" : 16,
      "JumpGroupSerial" : 0,
      "Message" : {
        "En" : "(Inhales)ー\n(Exhales)ー",
        "Jp" : "スー――\nハー――"
      },
      "MsgSerial" : 434480,
      "MsgType" : 0,
      "SetMotion" : 0,
      "TalkFaceType" : 0,
      "VoiceReqNo" : -1
    }, {
      "@class" : "org.sehkah.ddon.tools.extractor.common.logic.resource.entity.ui.MsgData",
      "DispTime" : 0,
      "DispType" : 0,
      "GmdIndex" : 17,
      "JumpGroupSerial" : 0,
      "Message" : {
        "En" : "Don't worry about it, \nit's just a deep breath.",
        "Jp" : "気にするな\n単なる深呼吸だ"
      },
      "MsgSerial" : 434481,
      "MsgType" : 0,
      "SetMotion" : 0,
      "TalkFaceType" : 0,
      "VoiceReqNo" : -1
    } ],
    "NameDispOff" : false,
    "NpcId" : 501,
    "NpcName" : {
      "En" : "Gurdolin",
      "Jp" : "ガルドリン"
    }
  }, {
    "@class" : "org.sehkah.ddon.tools.extractor.common.logic.resource.entity.ui.MsgGroup",
    "GroupNameSerial" : 0,
    "GroupSerial" : 17185,
    "GroupType" : 0,
    "GroupTypeName" : "MSG_GROUP_TYPE_NONE",
    "MsgData" : [ {
      "@class" : "org.sehkah.ddon.tools.extractor.common.logic.resource.entity.ui.MsgData",
      "DispTime" : 0,
      "DispType" : 0,
      "GmdIndex" : 18,
      "JumpGroupSerial" : 0,
      "Message" : {
        "En" : "Oh no—I'm so excited, \nI can't contain it!",
        "Jp" : "やば――ワクワクが止まらない！"
      },
      "MsgSerial" : 434482,
      "MsgType" : 0,
      "SetMotion" : 0,
      "TalkFaceType" : 0,
      "VoiceReqNo" : -1
    } ],
    "NameDispOff" : false,
    "NpcId" : 13,
    "NpcName" : {
      "En" : "Lise",
      "Jp" : "リズ"
    }
  }, {
    "@class" : "org.sehkah.ddon.tools.extractor.common.logic.resource.entity.ui.MsgGroup",
    "GroupNameSerial" : 0,
    "GroupSerial" : 17186,
    "GroupType" : 0,
    "GroupTypeName" : "MSG_GROUP_TYPE_NONE",
    "MsgData" : [ {
      "@class" : "org.sehkah.ddon.tools.extractor.common.logic.resource.entity.ui.MsgData",
      "DispTime" : 0,
      "DispType" : 0,
      "GmdIndex" : 19,
      "JumpGroupSerial" : 0,
      "Message" : {
        "En" : "Wow ―― I've got butterflies in my stomach.",
        "Jp" : "うう――みぞおちのあたりがキリキリします"
      },
      "MsgSerial" : 434483,
      "MsgType" : 0,
      "SetMotion" : 0,
      "TalkFaceType" : 0,
      "VoiceReqNo" : -1
    } ],
    "NameDispOff" : false,
    "NpcId" : 21,
    "NpcName" : {
      "En" : "Elliot",
      "Jp" : "エリオット"
    }
  }, {
    "@class" : "org.sehkah.ddon.tools.extractor.common.logic.resource.entity.ui.MsgGroup",
    "GroupNameSerial" : 0,
    "GroupSerial" : 15618,
    "GroupType" : 0,
    "GroupTypeName" : "MSG_GROUP_TYPE_NONE",
    "MsgData" : [ {
      "@class" : "org.sehkah.ddon.tools.extractor.common.logic.resource.entity.ui.MsgData",
      "DispTime" : 0,
      "DispType" : 0,
      "GmdIndex" : 20,
      "JumpGroupSerial" : 0,
      "Message" : {
        "En" : "Things have deteriorated since my time here— \nthat possibility is very high.",
        "Jp" : "わたしがいた時より状況は悪化している――\nその可能性はかなり高い"
      },
      "MsgSerial" : 377558,
      "MsgType" : 0,
      "SetMotion" : 0,
      "TalkFaceType" : 0,
      "VoiceReqNo" : -1
    }, {
      "@class" : "org.sehkah.ddon.tools.extractor.common.logic.resource.entity.ui.MsgData",
      "DispTime" : 0,
      "DispType" : 0,
      "GmdIndex" : 21,
      "JumpGroupSerial" : 0,
      "Message" : {
        "En" : "Shall we verify the safety of this area first?",
        "Jp" : "まず、このあたりの安全を確認しないか？"
      },
      "MsgSerial" : 434484,
      "MsgType" : 0,
      "SetMotion" : 0,
      "TalkFaceType" : 0,
      "VoiceReqNo" : -1
    } ],
    "NameDispOff" : false,
    "NpcId" : 22,
    "NpcName" : {
      "En" : "Loeg",
      "Jp" : "ロイグ"
    }
  }, {
    "@class" : "org.sehkah.ddon.tools.extractor.common.logic.resource.entity.ui.MsgGroup",
    "GroupNameSerial" : 0,
    "GroupSerial" : 17187,
    "GroupType" : 0,
    "GroupTypeName" : "MSG_GROUP_TYPE_NONE",
    "MsgData" : [ {
      "@class" : "org.sehkah.ddon.tools.extractor.common.logic.resource.entity.ui.MsgData",
      "DispTime" : 0,
      "DispType" : 0,
      "GmdIndex" : 22,
      "JumpGroupSerial" : 0,
      "Message" : {
        "En" : "Indeed, the air feels denser than in \nLestania, doesn't it? How are you faring?",
        "Jp" : "やはりレスタニアよりも空気が濃いですね？\nみなさんは大丈夫ですか？"
      },
      "MsgSerial" : 434485,
      "MsgType" : 0,
      "SetMotion" : 0,
      "TalkFaceType" : 0,
      "VoiceReqNo" : -1
    } ],
    "NameDispOff" : false,
    "NpcId" : 20,
    "NpcName" : {
      "En" : "Cecily",
      "Jp" : "セシリー"
    }
  }, {
    "@class" : "org.sehkah.ddon.tools.extractor.common.logic.resource.entity.ui.MsgGroup",
    "GroupNameSerial" : 0,
    "GroupSerial" : 17188,
    "GroupType" : 0,
    "GroupTypeName" : "MSG_GROUP_TYPE_NONE",
    "MsgData" : [ {
      "@class" : "org.sehkah.ddon.tools.extractor.common.logic.resource.entity.ui.MsgData",
      "DispTime" : 0,
      "DispType" : 0,
      "GmdIndex" : 23,
      "JumpGroupSerial" : 0,
      "Message" : {
        "En" : "I've never been afraid of humans, but \nexposed nature makes me feel uneasy.",
        "Jp" : "人間を怖いと思ったことはねえが\nむき出しの自然てのは、どうも落ち着かねえな"
      },
      "MsgSerial" : 434486,
      "MsgType" : 0,
      "SetMotion" : 0,
      "TalkFaceType" : 0,
      "VoiceReqNo" : -1
    } ],
    "NameDispOff" : false,
    "NpcId" : 501,
    "NpcName" : {
      "En" : "Gurdolin",
      "Jp" : "ガルドリン"
    }
  }, {
    "@class" : "org.sehkah.ddon.tools.extractor.common.logic.resource.entity.ui.MsgGroup",
    "GroupNameSerial" : 0,
    "GroupSerial" : 17189,
    "GroupType" : 0,
    "GroupTypeName" : "MSG_GROUP_TYPE_NONE",
    "MsgData" : [ {
      "@class" : "org.sehkah.ddon.tools.extractor.common.logic.resource.entity.ui.MsgData",
      "DispTime" : 0,
      "DispType" : 0,
      "GmdIndex" : 24,
      "JumpGroupSerial" : 0,
      "Message" : {
        "En" : "I didn't anticipate a grand welcome,\nyet I think it feels a little lonely, perhaps?",
        "Jp" : "大歓迎を期待していたわけじゃないけど\nちょっとサビシイかも？"
      },
      "MsgSerial" : 434487,
      "MsgType" : 0,
      "SetMotion" : 0,
      "TalkFaceType" : 0,
      "VoiceReqNo" : -1
    } ],
    "NameDispOff" : false,
    "NpcId" : 13,
    "NpcName" : {
      "En" : "Lise",
      "Jp" : "リズ"
    }
  }, {
    "@class" : "org.sehkah.ddon.tools.extractor.common.logic.resource.entity.ui.MsgGroup",
    "GroupNameSerial" : 0,
    "GroupSerial" : 17190,
    "GroupType" : 0,
    "GroupTypeName" : "MSG_GROUP_TYPE_NONE",
    "MsgData" : [ {
      "@class" : "org.sehkah.ddon.tools.extractor.common.logic.resource.entity.ui.MsgData",
      "DispTime" : 0,
      "DispType" : 0,
      "GmdIndex" : 25,
      "JumpGroupSerial" : 0,
      "Message" : {
        "En" : "I have no idea what might be lurking, \nso let's proceed with caution, carefully!",
        "Jp" : "何が潜んでいるかわかったもんじゃありません\n慎重に行きましょう、慎重に！"
      },
      "MsgSerial" : 434488,
      "MsgType" : 0,
      "SetMotion" : 0,
      "TalkFaceType" : 0,
      "VoiceReqNo" : -1
    } ],
    "NameDispOff" : false,
    "NpcId" : 21,
    "NpcName" : {
      "En" : "Elliot",
      "Jp" : "エリオット"
    }
  }, {
    "@class" : "org.sehkah.ddon.tools.extractor.common.logic.resource.entity.ui.MsgGroup",
    "GroupNameSerial" : 0,
    "GroupSerial" : 20092,
    "GroupType" : 0,
    "GroupTypeName" : "MSG_GROUP_TYPE_NONE",
    "MsgData" : [ {
      "@class" : "org.sehkah.ddon.tools.extractor.common.logic.resource.entity.ui.MsgData",
      "DispTime" : 0,
      "DispType" : 0,
      "GmdIndex" : 26,
      "JumpGroupSerial" : 0,
      "Message" : {
        "En" : "First, let's unlock the Portcrystal――",
        "Jp" : "まずは、礎を解放しちまうか――"
      },
      "MsgSerial" : 527745,
      "MsgType" : 0,
      "SetMotion" : 0,
      "TalkFaceType" : 0,
      "VoiceReqNo" : -1
    } ],
    "NameDispOff" : false,
    "NpcId" : 501,
    "NpcName" : {
      "En" : "Gurdolin",
      "Jp" : "ガルドリン"
    }
  }, {
    "@class" : "org.sehkah.ddon.tools.extractor.common.logic.resource.entity.ui.MsgGroup",
    "GroupNameSerial" : 0,
    "GroupSerial" : 15627,
    "GroupType" : 0,
    "GroupTypeName" : "MSG_GROUP_TYPE_NONE",
    "MsgData" : [ {
      "@class" : "org.sehkah.ddon.tools.extractor.common.logic.resource.entity.ui.MsgData",
      "DispTime" : 0,
      "DispType" : 0,
      "GmdIndex" : 27,
      "JumpGroupSerial" : 0,
      "Message" : {
        "En" : "Let's use this place as our base\nto venture out from here.",
        "Jp" : "ここを拠点にして、あちこちに足を伸ばそうぜ"
      },
      "MsgSerial" : 377567,
      "MsgType" : 0,
      "SetMotion" : 0,
      "TalkFaceType" : 0,
      "VoiceReqNo" : -1
    }, {
      "@class" : "org.sehkah.ddon.tools.extractor.common.logic.resource.entity.ui.MsgData",
      "DispTime" : 0,
      "DispType" : 0,
      "GmdIndex" : 28,
      "JumpGroupSerial" : 0,
      "Message" : {
        "En" : "Check on the state of the Rift Teleport \nand head back to Lestania. \nGo inform Joseph of your progress.",
        "Jp" : "おまえはリム転移の具合を確認しがてら\nレスタニアへ戻れ\nジョゼフに首尾を報告してこいよ"
      },
      "MsgSerial" : 377573,
      "MsgType" : 0,
      "SetMotion" : 0,
      "TalkFaceType" : 0,
      "VoiceReqNo" : -1
    } ],
    "NameDispOff" : false,
    "NpcId" : 501,
    "NpcName" : {
      "En" : "Gurdolin",
      "Jp" : "ガルドリン"
    }
  }, {
    "@class" : "org.sehkah.ddon.tools.extractor.common.logic.resource.entity.ui.MsgGroup",
    "GroupNameSerial" : 0,
    "GroupSerial" : 15628,
    "GroupType" : 0,
    "GroupTypeName" : "MSG_GROUP_TYPE_NONE",
    "MsgData" : [ {
      "@class" : "org.sehkah.ddon.tools.extractor.common.logic.resource.entity.ui.MsgData",
      "DispTime" : 0,
      "DispType" : 0,
      "GmdIndex" : 29,
      "JumpGroupSerial" : 0,
      "Message" : {
        "En" : "The gate has opened, \nallowing for Rift Teleport as well. \n――That's probably what it is, isn't it?",
        "Jp" : "ゲートが開通した結果、リム転移も可能になった\n――おそらく、そういうことですよね"
      },
      "MsgSerial" : 377568,
      "MsgType" : 0,
      "SetMotion" : 0,
      "TalkFaceType" : 0,
      "VoiceReqNo" : -1
    } ],
    "NameDispOff" : false,
    "NpcId" : 20,
    "NpcName" : {
      "En" : "Cecily",
      "Jp" : "セシリー"
    }
  }, {
    "@class" : "org.sehkah.ddon.tools.extractor.common.logic.resource.entity.ui.MsgGroup",
    "GroupNameSerial" : 0,
    "GroupSerial" : 15629,
    "GroupType" : 0,
    "GroupTypeName" : "MSG_GROUP_TYPE_NONE",
    "MsgData" : [ {
      "@class" : "org.sehkah.ddon.tools.extractor.common.logic.resource.entity.ui.MsgData",
      "DispTime" : 0,
      "DispType" : 0,
      "GmdIndex" : 30,
      "JumpGroupSerial" : 0,
      "Message" : {
        "En" : "After all, since this is a world of dragons,\nseems the basic rules remain the same.",
        "Jp" : "やっぱり竜の世界だから\n基本のルールは同じみたいだね"
      },
      "MsgSerial" : 377569,
      "MsgType" : 0,
      "SetMotion" : 0,
      "TalkFaceType" : 0,
      "VoiceReqNo" : -1
    }, {
      "@class" : "org.sehkah.ddon.tools.extractor.common.logic.resource.entity.ui.MsgData",
      "DispTime" : 0,
      "DispType" : 0,
      "GmdIndex" : 31,
      "JumpGroupSerial" : 0,
      "Message" : {
        "En" : "Indeed, yes, it's further back \nin the side area here――",
        "Jp" : "そうそう、ここの横手の奥の方――"
      },
      "MsgSerial" : 526295,
      "MsgType" : 0,
      "SetMotion" : 0,
      "TalkFaceType" : 0,
      "VoiceReqNo" : -1
    }, {
      "@class" : "org.sehkah.ddon.tools.extractor.common.logic.resource.entity.ui.MsgData",
      "DispTime" : 0,
      "DispType" : 0,
      "GmdIndex" : 32,
      "JumpGroupSerial" : 0,
      "Message" : {
        "En" : "Looks like there's a house nearby, \nshould we go greet them?",
        "Jp" : "家があるみたいなんだけど\nご挨拶しといた方がいいかな？"
      },
      "MsgSerial" : 526296,
      "MsgType" : 0,
      "SetMotion" : 0,
      "TalkFaceType" : 0,
      "VoiceReqNo" : -1
    } ],
    "NameDispOff" : false,
    "NpcId" : 13,
    "NpcName" : {
      "En" : "Lise",
      "Jp" : "リズ"
    }
  }, {
    "@class" : "org.sehkah.ddon.tools.extractor.common.logic.resource.entity.ui.MsgGroup",
    "GroupNameSerial" : 0,
    "GroupSerial" : 15630,
    "GroupType" : 0,
    "GroupTypeName" : "MSG_GROUP_TYPE_NONE",
    "MsgData" : [ {
      "@class" : "org.sehkah.ddon.tools.extractor.common.logic.resource.entity.ui.MsgData",
      "DispTime" : 0,
      "DispType" : 0,
      "GmdIndex" : 33,
      "JumpGroupSerial" : 0,
      "Message" : {
        "En" : "I shouldn't say this, but I'm glad to find that\nthis world isn't more developed than Lestania.",
        "Jp" : "これ、内緒ですけど――\nここがレスタニア以上に進んだ世界じゃなくて\n良かったと、ホッとしてます"
      },
      "MsgSerial" : 377570,
      "MsgType" : 0,
      "SetMotion" : 0,
      "TalkFaceType" : 0,
      "VoiceReqNo" : -1
    } ],
    "NameDispOff" : false,
    "NpcId" : 21,
    "NpcName" : {
      "En" : "Elliot",
      "Jp" : "エリオット"
    }
  }, {
    "@class" : "org.sehkah.ddon.tools.extractor.common.logic.resource.entity.ui.MsgGroup",
    "GroupNameSerial" : 0,
    "GroupSerial" : 15632,
    "GroupType" : 0,
    "GroupTypeName" : "MSG_GROUP_TYPE_NONE",
    "MsgData" : [ {
      "@class" : "org.sehkah.ddon.tools.extractor.common.logic.resource.entity.ui.MsgData",
      "DispTime" : 0,
      "DispType" : 0,
      "GmdIndex" : 34,
      "JumpGroupSerial" : 0,
      "Message" : {
        "En" : "Now that you are here,\nit's as if the problem is already solved.",
        "Jp" : "君たちが来てくれたのだから\n問題は解決したも同然"
      },
      "MsgSerial" : 377572,
      "MsgType" : 0,
      "SetMotion" : 0,
      "TalkFaceType" : 0,
      "VoiceReqNo" : -1
    }, {
      "@class" : "org.sehkah.ddon.tools.extractor.common.logic.resource.entity.ui.MsgData",
      "DispTime" : 0,
      "DispType" : 0,
      "GmdIndex" : 35,
      "JumpGroupSerial" : 0,
      "Message" : {
        "En" : "――I wasn't sure if saying that \nwould burden you so?\nBut it is my genuine sentiment.",
        "Jp" : "――なんて言ったら重荷になるかな？\nでも、これが本心なんだ"
      },
      "MsgSerial" : 434489,
      "MsgType" : 0,
      "SetMotion" : 0,
      "TalkFaceType" : 0,
      "VoiceReqNo" : -1
    } ],
    "NameDispOff" : false,
    "NpcId" : 22,
    "NpcName" : {
      "En" : "Loeg",
      "Jp" : "ロイグ"
    }
  }, {
    "@class" : "org.sehkah.ddon.tools.extractor.common.logic.resource.entity.ui.MsgGroup",
    "GroupNameSerial" : 0,
    "GroupSerial" : 17191,
    "GroupType" : 0,
    "GroupTypeName" : "MSG_GROUP_TYPE_NONE",
    "MsgData" : [ {
      "@class" : "org.sehkah.ddon.tools.extractor.common.logic.resource.entity.ui.MsgData",
      "DispTime" : 0,
      "DispType" : 0,
      "GmdIndex" : 36,
      "JumpGroupSerial" : 0,
      "Message" : {
        "En" : "Ah, I want souvenirs and stories so badly! \nBut you must be busy, right? \nI'll be patient—oh, I'll be patient!",
        "Jp" : "ああ、ノドから手が出るほど土産話が欲しい！\nでも、忙しいんだろ？\n我慢するよ――ああ、我慢我慢！"
      },
      "MsgSerial" : 434684,
      "MsgType" : 0,
      "SetMotion" : 0,
      "TalkFaceType" : 0,
      "VoiceReqNo" : -1
    } ],
    "NameDispOff" : false,
    "NpcId" : 3,
    "NpcName" : {
      "En" : "Klaus",
      "Jp" : "クラウス"
    }
  }, {
    "@class" : "org.sehkah.ddon.tools.extractor.common.logic.resource.entity.ui.MsgGroup",
    "GroupNameSerial" : 0,
    "GroupSerial" : 15631,
    "GroupType" : 0,
    "GroupTypeName" : "MSG_GROUP_TYPE_NONE",
    "MsgData" : [ {
      "@class" : "org.sehkah.ddon.tools.extractor.common.logic.resource.entity.ui.MsgData",
      "DispTime" : 0,
      "DispType" : 0,
      "GmdIndex" : 37,
      "JumpGroupSerial" : 0,
      "Message" : {
        "En" : "Your safe return is what matters most. \nNow, about what happened over there――",
        "Jp" : "無事の帰還、何よりだ\nさて、向こうでの出来事を――"
      },
      "MsgSerial" : 377571,
      "MsgType" : 0,
      "SetMotion" : 0,
      "TalkFaceType" : 0,
      "VoiceReqNo" : -1
    }, {
      "@class" : "org.sehkah.ddon.tools.extractor.common.logic.resource.entity.ui.MsgData",
      "DispTime" : 0,
      "DispType" : 0,
      "GmdIndex" : 38,
      "JumpGroupSerial" : 0,
      "Message" : {
        "En" : "I see――a world centered around the \"Core Tree\"",
        "Jp" : "そうか――\"芯なる樹\"を中心とする世界"
      },
      "MsgSerial" : 377574,
      "MsgType" : 0,
      "SetMotion" : 0,
      "TalkFaceType" : 0,
      "VoiceReqNo" : -1
    }, {
      "@class" : "org.sehkah.ddon.tools.extractor.common.logic.resource.entity.ui.MsgData",
      "DispTime" : 0,
      "DispType" : 0,
      "GmdIndex" : 39,
      "JumpGroupSerial" : 0,
      "Message" : {
        "En" : "Even in another world ruled by dragons,\nthings appear to differ quite a bit.\nHmm――fascinating.",
        "Jp" : "竜が司る世界と言っても、勝手が違うようだな\nふむ――興味深い"
      },
      "MsgSerial" : 377575,
      "MsgType" : 0,
      "SetMotion" : 0,
      "TalkFaceType" : 0,
      "VoiceReqNo" : -1
    }, {
      "@class" : "org.sehkah.ddon.tools.extractor.common.logic.resource.entity.ui.MsgData",
      "DispTime" : 0,
      "DispType" : 0,
      "GmdIndex" : 40,
      "JumpGroupSerial" : 0,
      "Message" : {
        "En" : "Then, we need to cure the ailing core tree, \nor this crisis won't be resolved――",
        "Jp" : "して、その、病んだ芯なる樹を治さねば\nこの事態は収まらないというわけか――"
      },
      "MsgSerial" : 377576,
      "MsgType" : 0,
      "SetMotion" : 0,
      "TalkFaceType" : 0,
      "VoiceReqNo" : -1
    } ],
    "NameDispOff" : false,
    "NpcId" : 4,
    "NpcName" : {
      "En" : "Joseph",
      "Jp" : "ジョゼフ"
    }
  } ],
  "NativeMsgGroupArrayNum" : 22
}